pymsalruntime/PyMsalRuntime.pyi
pymsalruntime/__init__.py
pymsalruntime/libmsalruntime.so
pymsalruntime/pymsalruntime.cpython-313-x86_64-linux-gnu.so
pymsalruntime-0.20.2.dist-info/METADATA
pymsalruntime-0.20.2.dist-info/WHEEL
pymsalruntime-0.20.2.dist-info/top_level.txt
pymsalruntime-0.20.2.dist-info/RECORD
