Metadata-Version: 2.4
Name: pymsalruntime
Version: 0.20.2
Summary: The MSALRuntime Python Interop Package
Author: Microsoft Corporation
Author-email: MSALRuntime@microsoft.com
License: MIT
Classifier: License :: OSI Approved :: MIT License
Requires-Python: >=3.6
Dynamic: author
Dynamic: author-email
Dynamic: classifier
Dynamic: license
Dynamic: requires-python
Dynamic: summary
